pylate_rs-1.0.4.dist-info/METADATA
pylate_rs-1.0.4.dist-info/WHEEL
pylate_rs-1.0.4.dist-info/licenses/LICENSE
pylate_rs/models/__init__.py
pylate_rs/models/colbert.py
pylate_rs/pylate_rs.cpython-39-aarch64-linux-gnu.so
pylate_rs-1.0.4.dist-info/RECORD
